pluralkit/__init__.py
pluralkit/__version__.py
pluralkit/v1/__init__.py
pluralkit/v1/client.py
pluralkit/v1/errors.py
pluralkit/v1/models.py
pluralkit/v1/utils.py
pluralkit/v2/__init__.py
pluralkit/v2/client.py
pluralkit/v2/errors.py
pluralkit/v2/models.py
pluralkit-1.2.1.dist-info/licenses/LICENSE
pluralkit-1.2.1.dist-info/METADATA
pluralkit-1.2.1.dist-info/WHEEL
pluralkit-1.2.1.dist-info/top_level.txt
pluralkit-1.2.1.dist-info/RECORD
