Metadata-Version: 2.4
Name: pluralkit
Version: 1.2.1
Summary: Python wrapper for PluralKit's API.
Home-page: https://github.com/almonds0166/pluralkit.py
Author: Madison Landry, Alyx Warner
Author-email: pkpy@mit.edu
License: MIT
Project-URL: Documentation, https://pluralkit.readthedocs.io/en/latest/
Project-URL: Issue tracker, https://github.com/almonds0166/pluralkit.py/issues
Classifier: Development Status :: 3 - Alpha
Classifier: Programming Language :: Python :: 3.6
Classifier: Programming Language :: Python :: 3.7
Classifier: Programming Language :: Python :: 3.8
Classifier: Programming Language :: Python :: 3.9
Classifier: Programming Language :: Python :: 3.10
Classifier: License :: OSI Approved :: MIT License
Classifier: Operating System :: OS Independent
Classifier: Intended Audience :: Developers
Classifier: Natural Language :: English
Classifier: Topic :: Internet
Classifier: Topic :: Software Development :: Libraries
Classifier: Topic :: Software Development :: Libraries :: Python Modules
Classifier: Topic :: Utilities
Requires-Python: >=3.6.0
License-File: LICENSE
Requires-Dist: httpx>=0.23.0
Requires-Dist: colour>=0.1
Requires-Dist: pytz>=2021
Provides-Extra: dev
Requires-Dist: Sphinx==5.0.1; extra == "dev"
Requires-Dist: sphinx-autodoc-typehints; extra == "dev"
Requires-Dist: sphinx-book-theme; extra == "dev"
Requires-Dist: sphinxcontrib-trio; extra == "dev"
Requires-Dist: mypy; extra == "dev"
Requires-Dist: types-pytz==2021.1.0; extra == "dev"
Requires-Dist: pytest; extra == "dev"
Requires-Dist: check-manifest; extra == "dev"
Requires-Dist: twine; extra == "dev"
Requires-Dist: wheel>=0.36.2; extra == "dev"
Dynamic: author
Dynamic: author-email
Dynamic: classifier
Dynamic: description
Dynamic: description-content-type
Dynamic: home-page
Dynamic: license
Dynamic: license-file
Dynamic: project-url
Dynamic: provides-extra
Dynamic: requires-dist
Dynamic: requires-python
Dynamic: summary
